<?xml version="1.0" encoding="UTF-8"?>
<GcnMcFileDb>
	<file>
		<description>Action Replay</description>
		<gamecode>D3GC</gamecode>
		<company>00</company>
		<search>
			<address>0x0000</address>
			<!-- TODO: Is V 1.14 the only known version? -->
			<gameDesc>^Action Replay V (\d)\.(\d{1,2})$</gameDesc>
			<fileDesc>^$</fileDesc>
		</search>
		<dirEntry>
			<filename>DATELCOD.BIN</filename>
			<bannerFormat>0x00</bannerFormat>
			<iconAddress>0x0040</iconAddress>
			<iconFormat>0x02</iconFormat>
			<iconSpeed>0x02</iconSpeed>
			<permission>0x04</permission>
			<length>2</length>
			<commentAddress>0x0000</commentAddress>
		</dirEntry>
	</file>
	<file>
		<description>Animal Crossing</description>
		<gamecode>GAFE</gamecode>
		<company>01</company>
		<search>
			<address>0x0000</address>
			<gameDesc>^Animal Crossing$</gameDesc>
			<!-- TODO: What characters are valid for the town name? -->
			<fileDesc>^(.*) Town Data$</fileDesc>
		</search>
		<dirEntry>
			<!-- TODO: Verify that the "A" in "MURA" is a slot ID,
			     and what are the valid slot ID? -->
			<filename>DobutsunomoriP_MUR$SL</filename>
			<slots>ABCDEFGHIJKLMNOPQRSTUVWXYZ</slots> <!-- FIXME: Not implemented yet... -->
			<bannerFormat>0x01</bannerFormat>
			<iconAddress>0x0040</iconAddress>
			<iconFormat>0x01</iconFormat>
			<iconSpeed>0x03</iconSpeed>
			<permission>0x04</permission>
			<length>57</length>
			<commentAddress>0x0000</commentAddress>
		</dirEntry>
	</file>
	<file>
		<description>Animal Crossing (NES Save Data)</description>
		<gamecode>GAFE</gamecode>
		<company>01</company>
		<search>
			<address>0x0000</address>
			<gameDesc>^Animal Crossing$</gameDesc>
			<fileDesc>^NES Save Data$</fileDesc>
		</search>
		<dirEntry>
			<filename>DobutsunomoriP_F_SAVE</filename>
			<bannerFormat>0x00</bannerFormat>
			<iconAddress>0x0040</iconAddress>
			<iconFormat>0x01</iconFormat>
			<iconSpeed>0x02</iconSpeed>
			<permission>0x04</permission>
			<length>1</length>
			<commentAddress>0x0000</commentAddress>
		</dirEntry>
	</file>
	<file>
		<description>Billy Hatcher and the Giant Egg</description>
		<gamecode>GEZE</gamecode>
		<company>8P</company>
		<search>
			<address>0x0000</address>
			<gameDesc>^Billy Hatcher$</gameDesc>
			<!-- Date format: MM/DD/YYYY HH:MM - Verify for PAL! -->
			<fileDesc>^(\d{2})/(\d{2})/(\d{4}) (\d{2}):(\d{2})$</fileDesc>
		</search>
		<dirEntry>
			<filename>billyhatcher</filename>
			<bannerFormat>0x02</bannerFormat>
			<iconAddress>0x0040</iconAddress>
			<iconFormat>0x02</iconFormat>
			<iconSpeed>0x03</iconSpeed>
			<permission>0x04</permission>
			<length>2</length>
			<commentAddress>0x0000</commentAddress>
		</dirEntry>
	</file>
	<file>
		<description>Crash Bandicoot: The Wrath of Cortex</description>
		<gamecode>GCBE</gamecode>
		<company>7D</company>
		<search>
			<address>0x0000</address>
			<gameDesc>^Crash Bandicoot: TWoC$</gameDesc>
			<fileDesc>^Save Game File$</fileDesc>
		</search>
		<dirEntry>
			<filename>CRASHWOC</filename>
			<bannerFormat>0x00</bannerFormat>
			<iconAddress>0x0040</iconAddress>
			<iconFormat>0x01</iconFormat>
			<iconSpeed>0x03</iconSpeed>
			<permission>0x04</permission>
			<length>1</length>
			<commentAddress>0x0000</commentAddress>
		</dirEntry>
	</file>
	<file>
		<description>F-Zero GX</description>
		<gamecode>GFZE</gamecode>
		<company>8P</company>
		<search>
			<address>0x0004</address>
			<gameDesc>^F-ZERO GX$</gameDesc>
			<!-- Date format: YY/MM/DD - Verify for PAL! -->
			<!-- TODO: Example field was "13/06/01 A" - what's the A for? -->
			<fileDesc>^(\d{2})/(\d{2})/(\d{2})</fileDesc>
			<!-- TODO: Checksum field? -->
		</search>
		<dirEntry>
			<filename>f_zero.dat</filename>
			<bannerFormat>0x02</bannerFormat>
			<iconAddress>0x0060</iconAddress>
			<iconFormat>0x02</iconFormat>
			<iconSpeed>0x03</iconSpeed>
			<permission>0x1C</permission>
			<length>4</length>
			<commentAddress>0x0004</commentAddress>
			<encrypted>true</encrypted>
		</dirEntry>
	</file>
	<file>
		<description>Luigi's Mansion</description>
		<gamecode>GLME</gamecode>
		<company>01</company>
		<search>
			<address>0x1C00</address>
			<gameDesc>^Luigi's Mansion$</gameDesc>
			<!-- Date format: M/D - Verify for PAL! -->
			<fileDesc>^Last saved on (\d{1,2})/(\d{1,2})$</fileDesc>
		</search>
		<checksum>
			<algorithm>AddInvDual16</algorithm>
			<address>0x3FFC</address>
			<range start="0x2000" length="0x1FFC" />
			<multiple instances="2" increment="0x2000" />
		</checksum>
		<dirEntry>
			<filename>LUIGI_MANSION_SAVEDATA_v3</filename>
			<bannerFormat>0x05</bannerFormat>
			<iconAddress>0x0000</iconAddress>
			<iconFormat>0x4041</iconFormat>
			<iconSpeed>0xFFFF</iconSpeed>
			<permission>0x04</permission>
			<length>3</length>
			<commentAddress>0x1C00</commentAddress>
		</dirEntry>
	</file>
	<file>
		<description>Mario Kart: Double Dash!!</description>
		<gamecode>GM4E</gamecode>
		<company>01</company>
		<search>
			<!-- Second block. FIXME: Implement block offsets. -->
			<!-- NOTE: This is also present at 0x4000... -->
			<address>0x2000</address>
			<gameDesc>^Mario Kart: Double Dash!!$</gameDesc>
			<!-- Date format: MM/DD/YY - Verify for PAL! -->
			<fileDesc>^Game Data (\d{2})/(\d{2})/(\d{2})$</fileDesc>
		</search>
		<dirEntry>
			<filename>MarioKart Double Dash!!</filename>
			<bannerFormat>0x01</bannerFormat>
			<iconAddress>0x0000</iconAddress>
			<iconFormat>0x15</iconFormat>
			<iconSpeed>0x2A</iconSpeed>
			<permission>0x04</permission>
			<length>3</length>
			<commentAddress>0x2000</commentAddress>
		</dirEntry>
	</file>
	<file>
		<description>Mario Party 4</description>
		<gamecode>GMPE</gamecode>
		<company>01</company>
		<search>
			<address>0x0000</address>
			<gameDesc>^Mario Party 4$</gameDesc>
			<!-- Date format: MM/DD/YYYY - Verify for PAL! -->
			<fileDesc>^File (\d)  (\d{2})/(\d{2})/(\d{4})$</fileDesc>
		</search>
		<dirEntry>
			<!-- TODO: $F1 needs a -1 modifier. -->
			<filename>MARIPA4BOX$F1</filename>
			<bannerFormat>0x01</bannerFormat>
			<iconAddress>0x0040</iconAddress>
			<iconFormat>0x0055</iconFormat>
			<iconSpeed>0x00AA</iconSpeed>
			<permission>0x04</permission>
			<length>2</length>
			<commentAddress>0x0000</commentAddress>
		</dirEntry>
	</file>
	<file>
		<description>Mario Party 5</description>
		<gamecode>GP5E</gamecode>
		<company>01</company>
		<search>
			<address>0x0000</address>
			<gameDesc>^Mario Party 5$</gameDesc>
			<!-- Date format: MM/DD/YYYY - Verify for PAL! -->
			<fileDesc>^(\d{2})/(\d{2})/(\d{4})$</fileDesc>
		</search>
		<dirEntry>
			<filename>MARIPA5</filename>
			<bannerFormat>0x01</bannerFormat>
			<iconAddress>0x0040</iconAddress>
			<iconFormat>0x0055</iconFormat>
			<iconSpeed>0x00AA</iconSpeed>
			<permission>0x04</permission>
			<length>5</length>
			<commentAddress>0x0000</commentAddress>
		</dirEntry>
	</file>
	<file>
		<description>Mario Party 6</description>
		<gamecode>GP6E</gamecode>
		<company>01</company>
		<search>
			<address>0x0000</address>
			<gameDesc>^Mario Party 6$</gameDesc>
			<!-- Date format: MM/DD/YYYY - Verify for PAL! -->
			<fileDesc>^(\d{2})/(\d{2})/(\d{4})$</fileDesc>
		</search>
		<dirEntry>
			<filename>MARIPA6</filename>
			<bannerFormat>0x05</bannerFormat>
			<iconAddress>0x0040</iconAddress>
			<iconFormat>0x0055</iconFormat>
			<iconSpeed>0x00AA</iconSpeed>
			<permission>0x04</permission>
			<length>5</length>
			<commentAddress>0x0000</commentAddress>
		</dirEntry>
	</file>
	<file>
		<description>Mario Party 7</description>
		<gamecode>GP7E</gamecode>
		<company>01</company>
		<search>
			<address>0x0000</address>
			<gameDesc>^Mario Party 7$</gameDesc>
			<!-- Date format: MM/DD/YYYY - Verify for PAL! -->
			<fileDesc>^(\d{2})/(\d{2})/(\d{4})$</fileDesc>
		</search>
		<dirEntry>
			<filename>MARIPA7</filename>
			<bannerFormat>0x05</bannerFormat>
			<iconAddress>0x0040</iconAddress>
			<iconFormat>0x0055</iconFormat>
			<iconSpeed>0x00AA</iconSpeed>
			<permission>0x04</permission>
			<length>6</length>
			<commentAddress>0x0000</commentAddress>
		</dirEntry>
	</file>
	<file>
		<!-- NOTE: PAL version uses a different file structure! -->
		<!-- User will need to select a preferred region. -->
		<description>Metroid Prime</description>
		<gamecode>GM8E</gamecode>
		<company>01</company>
		<search>
			<address>0x0004</address>
			<gameDesc>^Metroid Prime$</gameDesc>
			<!-- Date format: MM.DD.YY HH:mm -->
			<fileDesc>^(\d{2})\.(\d{2})\.(\d{2})  (\d{2}):(\d{2})$</fileDesc>
			<!-- TODO: Checksum field? -->
		</search>
		<dirEntry>
			<!-- NOTE: "A" is not a save slot!
			     "MetroidPrime B" is used for wear levelling,
			     and shouldn't show up normally.
			     All 3 save slots are in this file. -->
			<filename>MetroidPrime A</filename>
			<bannerFormat>0x01</bannerFormat>
			<iconAddress>0x0044</iconAddress>
			<iconFormat>0x01</iconFormat>
			<iconSpeed>0x02</iconSpeed>
			<permission>0x04</permission>
			<length>1</length>
			<commentAddress>0x0004</commentAddress>
		</dirEntry>
	</file>
	<file>
		<description>Metroid Prime 2: Echoes</description>
		<gamecode>G2ME</gamecode>
		<company>01</company>
		<search>
			<address>0x0004</address>
			<gameDesc>^Metroid Prime 2 Echoes$</gameDesc>
			<!-- Date format: MM.DD.YY HH:mm - Verify for PAL! -->
			<fileDesc>^(\d{2}).(\d{2}).(\d{2})  (\d{2}):(\d{2})$</fileDesc>
			<!-- TODO: Checksum field? -->
		</search>
		<dirEntry>
			<filename>MetroidPrime2</filename> <!-- TODO: Save slot? -->
			<bannerFormat>0x01</bannerFormat>
			<iconAddress>0x0044</iconAddress>
			<iconFormat>0x01</iconFormat>
			<iconSpeed>0x02</iconSpeed>
			<permission>0x04</permission>
			<length>3</length>
			<commentAddress>0x0004</commentAddress>
		</dirEntry>
	</file>
	<file>
		<description>Pac-Man World 2</description>
		<gamecode>GP2E</gamecode>
		<company>AF</company>
		<search>
			<address>0x0000</address>
			<gameDesc>^PAC-MAN WORLD 2$</gameDesc>
			<fileDesc>^\(C\) 2002 NAMCO$</fileDesc>
		</search>
		<dirEntry>
			<filename>PMW2SAVE</filename>
			<bannerFormat>0x02</bannerFormat>
			<iconAddress>0x0040</iconAddress>
			<iconFormat>0x2AAA</iconFormat>
			<iconSpeed>0x2AAA</iconSpeed>
			<permission>0x04</permission>
			<length>8</length>
			<commentAddress>0x0000</commentAddress>
		</dirEntry>
	</file>
	<file>
		<description>Paper Mario: The Thousand Year Door</description>
		<gamecode>G8ME</gamecode>
		<company>01</company>
		<search>
			<address>0x0000</address>
			<gameDesc>^Paper Mario$</gameDesc>
			<!-- Date format: MM/DD, with leading spaces - Verify for PAL! -->
			<!-- NOTE: Months less than 10 will have a leading space;
			     however, mcrecover trims spaces from descriptions! -->
			<fileDesc>^( \d|\d{1,2})/( \d|\d{2}) save data$</fileDesc>
		</search>
		<dirEntry>
			<filename>mariost_save_file</filename>
			<bannerFormat>0x02</bannerFormat>
			<iconAddress>0x0040</iconAddress>
			<iconFormat>0x01</iconFormat>
			<iconSpeed>0x02</iconSpeed>
			<permission>0x04</permission>
			<length>17</length>
			<commentAddress>0x0000</commentAddress>
		</dirEntry>
	</file>
	<file>
		<description>Puyo Pop Fever (System File)</description>
		<gamecode>GPUE</gamecode>
		<company>8P</company>
		<search>
			<address>0x0000</address>
			<gameDesc>^Puyo Pop Fever$</gameDesc>
			<fileDesc>^System File$</fileDesc>
		</search>
		<dirEntry>
			<filename>Puyo Pop Fever System</filename>
			<bannerFormat>0x00</bannerFormat>
			<iconAddress>0x0040</iconAddress>
			<iconFormat>0x01</iconFormat>
			<iconSpeed>0x03</iconSpeed>
			<permission>0x04</permission>
			<length>1</length>
			<commentAddress>0x0000</commentAddress>
		</dirEntry>
	</file>
	<file>
		<description>Puyo Pop Fever (Replay)</description>
		<gamecode>GPUE</gamecode>
		<company>8P</company>
		<search>
			<address>0x0000</address>
			<gameDesc>^Puyo Pop Fever$</gameDesc>
			<fileDesc>^Replay(\d{2}) File$</fileDesc>
		</search>
		<dirEntry>
			<filename>Puyo Pop Fever Replay$F1</filename>
			<bannerFormat>0x00</bannerFormat>
			<iconAddress>0x0040</iconAddress>
			<iconFormat>0x01</iconFormat>
			<iconSpeed>0x03</iconSpeed>
			<permission>0x04</permission>
			<length>3</length>
			<commentAddress>0x0000</commentAddress>
		</dirEntry>
	</file>
	<file>
		<description>Shadow the Hedgehog</description>
		<gamecode>GUPE</gamecode>
		<company>8P</company>
		<search>
			<address>0x0000</address>
			<gameDesc>^SHADOW THE HEDGEHOG$</gameDesc>
			<fileDesc>^GAME DATA$</fileDesc>
		</search>
		<dirEntry>
			<filename>SHADOWTHEHEDGEHOG</filename>
			<bannerFormat>0x02</bannerFormat>
			<iconAddress>0x0040</iconAddress>
			<iconFormat>0x02</iconFormat>
			<iconSpeed>0x02</iconSpeed>
			<permission>0x04</permission>
			<length>2</length>
			<commentAddress>0x0000</commentAddress>
		</dirEntry>
	</file>
	<file>
		<description>Sonic Adventure DX: Director's Cut</description>
		<gamecode>GXSE</gamecode>
		<company>8P</company>
		<search>
			<address>0x0000</address>
			<gameDesc>^Sonic Adventure DX  File (\d)$</gameDesc>
			<fileDesc>^Emblem collected :(  \d| \d{2}|\d{3})$</fileDesc>
		</search>
		<checksum>
			<algorithm>CRC-16</algorithm>
			<!-- NOTE: Stored as uint32_t in the file; we only need uint16_t. -->
			<address>0x1442</address>
			<range start="0x1444" length="0x056C" />
		</checksum>
		<dirEntry>
			<filename>SONICADVENTURE_DX_PLAYRECORD_$G1</filename>
			<bannerFormat>0x01</bannerFormat>
			<iconAddress>0x0040</iconAddress>
			<iconFormat>0x01</iconFormat>
			<iconSpeed>0x01</iconSpeed>
			<permission>0x04</permission>
			<length>1</length>
			<commentAddress>0x0000</commentAddress>
		</dirEntry>
	</file>
	<file>
		<description>Sonic Adventure DX: Director's Cut (Chao Garden)</description>
		<gamecode>GXSE</gamecode>
		<company>8P</company>
		<search>
			<address>0x0000</address>
			<gameDesc>^Sonic Adventure DX$</gameDesc>
			<fileDesc>^Chao Garden$</fileDesc>
		</search>
		<checksum>
			<algorithm>SonicChaoGarden</algorithm>
			<!-- NOTE: Checksum is NOT a contiguous uint32_t.
			     This is the starting address of the entire
			     checksum block. -->
			<!-- Banner+icons take up 0x3040 bytes. -->
			<!-- Chao Garden checksum is at 0xC818 after the banner. -->
			<address>0xF858</address>
			<range start="0x3040" length="0xC820" />
		</checksum>
		<dirEntry>
			<filename>SONICADVENTURE_DX_CHAOGARDEN</filename>
			<bannerFormat>0x01</bannerFormat>
			<iconAddress>0x0040</iconAddress>
			<iconFormat>0x5555</iconFormat>
			<iconSpeed>0xAAAA</iconSpeed>
			<permission>0x0C</permission>
			<length>8</length>
			<commentAddress>0x0000</commentAddress>
		</dirEntry>
	</file>
	<file>
		<description>Sonic Adventure 2: Battle</description>
		<gamecode>GSNE</gamecode>
		<company>8P</company>
		<search>
			<address>0x0000</address>
			<gameDesc>^SONIC ADVENTURE 2 BATTLE$</gameDesc>
			<fileDesc>^FILE(\d{2}):(  \d| \d{2}|\d{3}) Emblems?$</fileDesc>
		</search>
		<checksum>
			<algorithm>AddBytes32</algorithm>
			<address>0x2840</address>
			<range start="0x2844" length="0x34A0" />
		</checksum>
		<dirEntry>
			<filename>SONIC2B__S$F1</filename>
			<bannerFormat>0x06</bannerFormat>
			<iconAddress>0x0040</iconAddress>
			<iconFormat>0x0A</iconFormat>
			<iconSpeed>0x0F</iconSpeed>
			<permission>0x04</permission>
			<length>3</length>
			<commentAddress>0x0000</commentAddress>
		</dirEntry>
	</file>
	<file>
		<description>Sonic Adventure 2: Battle (Chao Garden)</description>
		<gamecode>GSNE</gamecode>
		<company>8P</company>
		<search>
			<address>0x0000</address>
			<gameDesc>^SONIC ADVENTURE 2 BATTLE$</gameDesc>
			<fileDesc>^CHAO GARDEN DATA$</fileDesc>
		</search>
		<checksum>
			<algorithm>SonicChaoGarden</algorithm>
			<!-- NOTE: Checksum is NOT a contiguous uint32_t.
			     This is the starting address of the entire
			     checksum block. -->
			<!-- Banner+icons take up 0x3040 bytes. -->
			<!-- Chao Garden checksum is at 0xCA64 after the banner. -->
			<address>0xFAA4</address>
			<range start="0x3040" length="0xCA6C" />
		</checksum>
		<dirEntry>
			<filename>SONIC2B__ALF</filename>
			<bannerFormat>0xCD</bannerFormat>
			<iconAddress>0x0040</iconAddress>
			<iconFormat>0x5555</iconFormat>
			<iconSpeed>0x5555</iconSpeed>
			<permission>0x0C</permission>
			<length>8</length>
			<commentAddress>0x0000</commentAddress>
		</dirEntry>
	</file>
	<file>
		<description>Sonic Gems Collection</description>
		<gamecode>G2XE</gamecode>
		<company>8P</company>
		<search>
			<address>0x0000</address>
			<gameDesc>^SONIC GEMS COLLECTION$</gameDesc>
			<!-- Date format: MM/DD - Verify for PAL! -->
			<fileDesc>^SETTING DATA (\d{2})/(\d{2})$</fileDesc>
		</search>
		<dirEntry>
			<filename>SONIC GEMS_00</filename>
			<bannerFormat>0x02</bannerFormat>
			<iconAddress>0x0040</iconAddress>
			<iconFormat>0x02</iconFormat>
			<iconSpeed>0x02</iconSpeed>
			<permission>0x04</permission>
			<length>2</length>
			<commentAddress>0x0000</commentAddress>
		</dirEntry>
	</file>
	<file>
		<description>Sonic Gems Collection (Sonic R)</description>
		<gamecode>G2XE</gamecode>
		<company>8P</company>
		<search>
			<address>0x0000</address>
			<gameDesc>^SONIC GEMS COLLECTION$</gameDesc>
			<fileDesc>^SONIC R : Game Data$</fileDesc>
		</search>
		<dirEntry>
			<filename>SONIC_R</filename>
			<bannerFormat>0x01</bannerFormat>
			<iconAddress>0x0040</iconAddress>
			<iconFormat>0x01</iconFormat>
			<iconSpeed>0x03</iconSpeed>
			<permission>0x04</permission>
			<length>4</length>
			<commentAddress>0x0000</commentAddress>
		</dirEntry>
	</file>
	<file>
		<description>Sonic Gems Collection (Sonic the Fighters)</description>
		<gamecode>G2XE</gamecode>
		<company>8P</company>
		<search>
			<address>0x0000</address>
			<gameDesc>^SONIC GEMS COLLECTION$</gameDesc>
			<fileDesc>^SONIC F : SYSTEM FILE$</fileDesc>
		</search>
		<dirEntry>
			<filename>STF.DAT</filename>
			<bannerFormat>0x02</bannerFormat>
			<iconAddress>0x0040</iconAddress>
			<iconFormat>0x02</iconFormat>
			<iconSpeed>0x03</iconSpeed>
			<permission>0x04</permission>
			<length>4</length>
			<commentAddress>0x0000</commentAddress>
		</dirEntry>
	</file>
	<file>
		<description>Sonic Heroes</description>
		<gamecode>G9SE</gamecode>
		<company>8P</company>
		<search>
			<address>0x0000</address>
			<gameDesc>^SONIC HEROES : (\d{2})$</gameDesc>
			<fileDesc>^EMBLEM : (\d{3})$</fileDesc>
		</search>
		<dirEntry>
			<!-- TODO: $G1 needs a -1 modifier. -->
			<filename>SONICHEROES_$G1</filename>
			<bannerFormat>0x02</bannerFormat>
			<iconAddress>0x0040</iconAddress>
			<iconFormat>0x02</iconFormat>
			<iconSpeed>0x02</iconSpeed>
			<permission>0x04</permission>
			<length>2</length>
			<commentAddress>0x0000</commentAddress>
		</dirEntry>
	</file>
	<file>
		<description>Sonic Mega Collection</description>
		<gamecode>GSOE</gamecode>
		<company>8P</company>
		<search>
			<address>0x0000</address>
			<gameDesc>^Sonic Mega Collection$</gameDesc>
			<!-- Date format: MM/DD HH:MM - Verify for PAL! -->
			<fileDesc>^System File (\d{2})/(\d{2}) (\d{2}):(\d{2})$</fileDesc>
		</search>
		<dirEntry>
			<filename>S_MEGA_SYS</filename>
			<bannerFormat>0x02</bannerFormat>
			<iconAddress>0x0040</iconAddress>
			<iconFormat>0x02</iconFormat>
			<iconSpeed>0x03</iconSpeed>
			<permission>0x04</permission>
			<length>2</length>
			<commentAddress>0x0000</commentAddress>
		</dirEntry>
	</file>
	<file>
		<description>Sonic Riders</description>
		<gamecode>G2XE</gamecode>
		<company>8P</company>
		<search>
			<address>0x1400</address>
			<gameDesc>^SONIC RIDERS$</gameDesc>
			<!-- Date format: MM/DD/YY - Verify for PAL! -->
			<fileDesc>^Game Data\.(\d{2}): (\d{2})/(\d{2})/(\d{2})$</fileDesc>
		</search>
		<dirEntry>
			<filename>SONICRIDERS_GAMEDATA_$F1</filename>
			<bannerFormat>0x01</bannerFormat>
			<iconAddress>0x0000</iconAddress>
			<iconFormat>0x01</iconFormat>
			<iconSpeed>0x03</iconSpeed>
			<permission>0x04</permission>
			<length>1</length>
			<commentAddress>0x1400</commentAddress>
		</dirEntry>
	</file>
	<file>
		<description>Super Mario Sunshine</description>
		<gamecode>GMSE</gamecode>
		<company>01</company>
		<search>
			<address>0x0004</address>
			<gameDesc>^Super Mario Sunshine$</gameDesc>
			<!-- Date format: M/D - Verify for PAL! -->
			<fileDesc>^(\d{1,2})/(\d{1,2}) Save Data$</fileDesc>
		</search>
		<checksum>
			<algorithm>AddInvDual16</algorithm>
			<address>0x3FFC</address>
			<range start="0x2000" length="0x1FFC" />
			<multiple instances="6" increment="0x2000" />
		</checksum>
		<dirEntry>
			<filename>super_mario_sunshine</filename>
			<bannerFormat>0x01</bannerFormat>
			<iconAddress>0x0044</iconAddress>
			<iconFormat>0x05</iconFormat>
			<iconSpeed>0x0F</iconSpeed>
			<permission>0x04</permission>
			<length>7</length>
			<commentAddress>0x0004</commentAddress>
		</dirEntry>
	</file>
	<file>
		<description>Super Monkey Ball 2</description>
		<gamecode>GM2E</gamecode>
		<company>8P</company>
		<search>
			<address>0x0004</address>
			<gameDesc>^Super Monkey Ball 2$</gameDesc>
			<fileDesc>^Game Data$</fileDesc>
			<!-- TODO: Checksum field? -->
		</search>
		<dirEntry>
			<filename>super_monkey_ball_2.dat</filename>
			<bannerFormat>0x02</bannerFormat>
			<iconAddress>0x0060</iconAddress>
			<iconFormat>0x02</iconFormat>
			<iconSpeed>0x03</iconSpeed>
			<permission>0x04</permission>
			<length>2</length>
			<commentAddress>0x0004</commentAddress>
		</dirEntry>
	</file>
	<file>
		<description>Super Smash Bros. Melee</description>
		<gamecode>GALE</gamecode>
		<company>01</company>
		<search>
			<address>0x0000</address>
			<gameDesc>^Super Smash Bros. Melee$</gameDesc>
			<!-- Date format: YYYY/MM/DD - Verify for PAL! -->
			<fileDesc>^Game Data (\d{4})/(\d{2})/(\d{2})$</fileDesc>
		</search>
		<dirEntry>
			<filename>SuperSmashBros0110290334</filename>
			<bannerFormat>0x02</bannerFormat>
			<iconAddress>0x0040</iconAddress>
			<iconFormat>0x01</iconFormat>
			<iconSpeed>0x03</iconSpeed>
			<permission>0x04</permission>
			<length>11</length>
			<commentAddress>0x0000</commentAddress>
		</dirEntry>
	</file>
	<file>
		<description>The Legend of Zelda: Collector's Edition (Zelda 1)</description>
		<gamecode>PZLE</gamecode>
		<company>01</company>
		<search>
			<address>0x1C00</address>
			<gameDesc>^Zelda: Collector's Edition$</gameDesc>
			<fileDesc>^THE LEGEND OF ZELDA$</fileDesc>
		</search>
		<dirEntry>
			<filename>NES_ZELDA1_SAVE</filename>
			<bannerFormat>0x05</bannerFormat>
			<iconAddress>0x0000</iconAddress>
			<iconFormat>0x15</iconFormat>
			<iconSpeed>0x3F</iconSpeed>
			<permission>0x04</permission>
			<length>3</length>
			<commentAddress>0x1C00</commentAddress>
		</dirEntry>
	</file>
	<file>
		<description>The Legend of Zelda: Collector's Edition (Zelda 2)</description>
		<gamecode>PZLE</gamecode>
		<company>01</company>
		<search>
			<address>0x1C00</address>
			<gameDesc>^Zelda: Collector's Edition$</gameDesc>
			<fileDesc>^THE ADVENTURE OF LINK$</fileDesc>
		</search>
		<dirEntry>
			<filename>NES_ZELDA2_SAVE</filename>
			<bannerFormat>0x05</bannerFormat>
			<iconAddress>0x0000</iconAddress>
			<iconFormat>0x15</iconFormat>
			<iconSpeed>0x3F</iconSpeed>
			<permission>0x04</permission>
			<length>3</length>
			<commentAddress>0x1C00</commentAddress>
		</dirEntry>
	</file>
	<file>
		<description>The Legend of Zelda: Collector's Edition (Ocarina of Time)</description>
		<gamecode>PZLE</gamecode>
		<company>01</company>
		<search>
			<address>0x002C</address>
			<gameDesc>^Zelda: Collector's Edition$</gameDesc>
			<fileDesc>^OCARINA OF TIME$</fileDesc>
		</search>
		<dirEntry>
			<filename>ZELDA1</filename>
			<bannerFormat>0x06</bannerFormat>
			<iconAddress>0x006C</iconAddress>
			<iconFormat>0x2A</iconFormat>
			<iconSpeed>0x3F</iconSpeed>
			<permission>0x04</permission>
			<length>9</length>
			<commentAddress>0x002C</commentAddress>
		</dirEntry>
	</file>
	<file>
		<description>The Legend of Zelda: Collector's Edition (Majora's Mask)</description>
		<gamecode>PZLE</gamecode>
		<company>01</company>
		<search>
			<address>0x002C</address>
			<gameDesc>^Zelda: Collector's Edition$</gameDesc>
			<fileDesc>^MAJORA'S MASK$</fileDesc>
		</search>
		<dirEntry>
			<filename>ZELDA2</filename>
			<bannerFormat>0x06</bannerFormat>
			<iconAddress>0x006C</iconAddress>
			<iconFormat>0x2A</iconFormat>
			<iconSpeed>0x3F</iconSpeed>
			<permission>0x04</permission>
			<length>21</length>
			<commentAddress>0x002C</commentAddress>
		</dirEntry>
	</file>
	<file>
		<description>The Legend of Zelda: Four Swords Adventures</description>
		<gamecode>G4SE</gamecode>
		<company>01</company>
		<search>
			<address>0x1C00</address>
			<gameDesc>^Four Swords Adventures$</gameDesc>
			<!-- Date format: M/D - Verify for PAL! -->
			<fileDesc>^(\d{1,2})/(\d{1,2}) Save Data$</fileDesc>
		</search>
		<dirEntry>
			<filename>gc4sword</filename>
			<bannerFormat>0x01</bannerFormat>
			<iconAddress>0x0000</iconAddress>
			<iconFormat>0x01</iconFormat>
			<iconSpeed>0x03</iconSpeed>
			<permission>0x04</permission>
			<length>3</length>
			<commentAddress>0x1C00</commentAddress>
		</dirEntry>
	</file>
	<file>
		<description>The Legend of Zelda: Ocarina of Time / Master Quest</description>
		<gamecode>D43E</gamecode>
		<company>01</company>
		<search>
			<address>0x002C</address>
			<gameDesc>^Zelda: Ocarina of Time$</gameDesc>
			<!-- Date format: M/D - Verify for PAL! -->
			<fileDesc>^(\d{1,2})/(\d{1,2}) Save Data$</fileDesc>
		</search>
		<dirEntry>
			<filename>ZELDA</filename>
			<bannerFormat>0x06</bannerFormat>
			<iconAddress>0x006C</iconAddress>
			<iconFormat>0x2A</iconFormat>
			<iconSpeed>0x2A</iconSpeed>
			<permission>0x04</permission>
			<length>15</length>
			<commentAddress>0x002C</commentAddress>
		</dirEntry>
	</file>
	<file>
		<description>The Legend of Zelda: The Wind Waker</description>
		<gamecode>GZLE</gamecode>
		<company>01</company>
		<search>
			<address>0x1C00</address>
			<gameDesc>^Zelda: The Wind Waker$</gameDesc>
			<!-- Date format: M/D - Verify for PAL! -->
			<fileDesc>^(\d{1,2})/(\d{1,2}) Save Data$</fileDesc>
		</search>
		<dirEntry>
			<filename>gczelda</filename>
			<bannerFormat>0x01</bannerFormat>
			<iconAddress>0x0000</iconAddress>
			<iconFormat>0x01</iconFormat>
			<iconSpeed>0x03</iconSpeed>
			<permission>0x04</permission>
			<length>12</length>
			<commentAddress>0x1C00</commentAddress>
		</dirEntry>
	</file>
	<file>
		<description>The Legend of Zelda: Twilight Princess</description>
		<gamecode>GZLE</gamecode>
		<company>01</company>
		<search>
			<!-- Second block. FIXME: Implement block offsets. -->
			<address>0x2400</address>
			<gameDesc>^Zelda: Twilight Princess$</gameDesc>
			<!-- Date format: M/D - Verify for PAL! -->
			<fileDesc>^(\d{1,2})/(\d{1,2}) Save Data$</fileDesc>
		</search>
		<dirEntry>
			<filename>gczelda2</filename>
			<bannerFormat>0x05</bannerFormat>
			<iconAddress>0x0000</iconAddress>
			<iconFormat>0x0155</iconFormat>
			<iconSpeed>0x0155</iconSpeed>
			<permission>0x04</permission>
			<length>4</length>
			<commentAddress>0x2400</commentAddress>
		</dirEntry>
	</file>
</GcnMcFileDb>
